<?xml version="1.0" encoding="UTF-8"?>
<!DOCTYPE mapper PUBLIC "-//mybatis.org//DTD Mapper 3.0//EN" "http://mybatis.org/dtd/mybatis-3-mapper.dtd">
<mapper namespace="com.SmartHire.adminService.mapper.InterviewMapper">

    <!-- 通用查询映射结果 -->
    <resultMap id="BaseResultMap" type="com.SmartHire.adminService.model.Interview">
        <id column="id" property="id" />
        <result column="application_id" property="applicationId" />
        <result column="interview_type" property="interviewType" />
        <result column="interview_round" property="interviewRound" />
        <result column="interview_time" property="interviewTime" />
        <result column="duration" property="duration" />
        <result column="location" property="location" />
        <result column="meeting_link" property="meetingLink" />
        <result column="interviewer" property="interviewer" />
        <result column="status" property="status" />
        <result column="feedback" property="feedback" />
        <result column="result" property="result" />
        <result column="created_at" property="createdAt" />
        <result column="updated_at" property="updatedAt" />
    </resultMap>

    <!-- 通用查询结果列 -->
    <sql id="Base_Column_List">
        id, application_id, interview_type, interview_round, interview_time, duration, location, meeting_link, interviewer, status, feedback, result, created_at, updated_at
    </sql>

</mapper>
